CHANGES.rst
COPYRIGHT
LICENSE
MANIFEST.in
README.rst
setup.cfg
setup.py
tox.ini
tests/test_autodoc.py
tests/sample/conf.py
tests/sample/contents.rst
tests/sample/sampleapp.py
waeup/__init__.py
waeup.sphinx.autodoc.egg-info/PKG-INFO
waeup.sphinx.autodoc.egg-info/SOURCES.txt
waeup.sphinx.autodoc.egg-info/dependency_links.txt
waeup.sphinx.autodoc.egg-info/namespace_packages.txt
waeup.sphinx.autodoc.egg-info/not-zip-safe
waeup.sphinx.autodoc.egg-info/requires.txt
waeup.sphinx.autodoc.egg-info/top_level.txt
waeup/sphinx/__init__.py
waeup/sphinx/autodoc.py