Metadata-Version: 1.1
Name: waeup.sphinx.autodoc
Version: 0.1.1
Summary: More Zope compatible autodocumenters for Sphinx.
Home-page: http://pypi.python.org/pypi/waeup.sphinx.autodoc
Author: Uli Fouquet
Author-email: uli@gnufix.de
License: GPL 3.0
Keywords: sphinx autodoc grok zope waeup documenter
Platform: UNKNOWN
Classifier: Development Status :: 3 - Alpha
Classifier: Environment :: Console
Classifier: Environment :: Web Environment
Classifier: Framework :: Sphinx
Classifier: Framework :: Sphinx :: Extension
Classifier: Intended Audience :: Developers
Classifier: Intended Audience :: Education
Classifier: License :: OSI Approved :: GNU General Public License v3 or later (GPLv3+)
Classifier: Operating System :: POSIX :: Linux
Classifier: Programming Language :: Python :: 2
Classifier: Programming Language :: Python :: 2.6
Classifier: Programming Language :: Python :: 2.7
Classifier: Programming Language :: Python :: Implementation :: CPython
Classifier: Topic :: Documentation
Classifier: Topic :: Documentation :: Sphinx
Classifier: Topic :: Utilities
